{
  "Meal at an Inexpensive Restaurant": "500.00\u00a0\u20b9",
  "Meal for Two at a Mid-Range Restaurant (Three Courses, Without Drinks)": "2,000.00\u00a0\u20b9",
  "Combo Meal at McDonald's (or Equivalent Fast-Food Meal)": "350.00\u00a0\u20b9",
  "Domestic Draft Beer (0.5 Liter)": "220.00\u00a0\u20b9",
  "Imported Beer (0.33 Liter Bottle)": "248.57\u00a0\u20b9",
  "Cappuccino (Regular Size)": "207.21\u00a0\u20b9",
  "Soft Drink (Coca-Cola or Pepsi, 0.33 Liter Bottle)": "41.61\u00a0\u20b9",
  "Bottled Water (0.33 Liter)": "15.59\u00a0\u20b9",
  "Milk (Regular, 1 Liter)": "66.53\u00a0\u20b9",
  "Fresh White Bread (500 g Loaf)": "51.77\u00a0\u20b9",
  "White Rice (1 kg)": "77.11\u00a0\u20b9",
  "Eggs (12, Large Size)": "107.83\u00a0\u20b9",
  "Local Cheese (1 kg)": "419.17\u00a0\u20b9",
  "Chicken Fillets (1 kg)": "331.35\u00a0\u20b9",
  "Buffalo Round or Equivalent Back Leg Red Meat (1 kg)": "595.33\u00a0\u20b9",
  "Apples (1 kg)": "176.50\u00a0\u20b9",
  "Bananas (1 kg)": "71.74\u00a0\u20b9",
  "Oranges (1 kg)": "99.60\u00a0\u20b9",
  "Tomatoes (1 kg)": "54.50\u00a0\u20b9",
  "Potatoes (1 kg)": "33.33\u00a0\u20b9",
  "Onions (1 kg)": "40.37\u00a0\u20b9",
  "Lettuce (1 Head)": "48.55\u00a0\u20b9",
  "Bottled Water (1.5 Liter)": "29.10\u00a0\u20b9",
  "Bottle of Wine (Mid-Range)": "900.00\u00a0\u20b9",
  "Domestic Beer (0.5 Liter Bottle)": "176.04\u00a0\u20b9",
  "Cigarettes (Pack of 20, Marlboro)": "345.00\u00a0\u20b9",
  "One-Way Ticket (Local Transport)": "40.00\u00a0\u20b9",
  "Monthly Public Transport Pass (Regular Price)": "1,500.00\u00a0\u20b9",
  "Taxi Start (Standard Tariff)": "85.00\u00a0\u20b9",
  "Taxi 1 km (Standard Tariff)": "25.00\u00a0\u20b9",
  "Taxi 1 Hour Waiting (Standard Tariff)": "105.00\u00a0\u20b9",
  "Gasoline (1 Liter)": "99.03\u00a0\u20b9",
  "Volkswagen Golf 1.5 (or Equivalent New Compact Car)": "1,300,000.00\u00a0\u20b9",
  "Toyota Corolla Sedan 1.6 (or Equivalent New Mid-Size Car)": "2,094,304.35\u00a0\u20b9",
  "Basic Utilities for 85 m2 Apartment (Electricity, Heating, Cooling, Water, Garbage)": "4,906.58\u00a0\u20b9",
  "Mobile Phone Plan (Monthly, with Calls and 10GB+ Data)": "409.81\u00a0\u20b9",
  "Broadband Internet (Unlimited Data, 60 Mbps or Higher)": "765.70\u00a0\u20b9",
  "Monthly Fitness Club Membership": "1,866.67\u00a0\u20b9",
  "Tennis Court Rental (1 Hour, Weekend)": "845.00\u00a0\u20b9",
  "Cinema Ticket (International Release)": "500.00\u00a0\u20b9",
  "Private Full-Day Preschool or Kindergarten, Monthly Fee per Child": "6,162.88\u00a0\u20b9",
  "International Primary School, Annual Tuition per Child": "173,764.71\u00a0\u20b9",
  "Jeans (Levi's 501 or Similar)": "2,399.97\u00a0\u20b9",
  "Summer Dress in a Chain Store (e.g. Zara or H&M)": "2,777.74\u00a0\u20b9",
  "Nike Running Shoes (Mid-Range)": "5,344.83\u00a0\u20b9",
  "Men's Leather Business Shoes": "4,520.00\u00a0\u20b9",
  "1 Bedroom Apartment in City Centre": "24,357.14\u00a0\u20b9",
  "1 Bedroom Apartment Outside of City Centre": "15,080.00\u00a0\u20b9",
  "3 Bedroom Apartment in City Centre": "70,227.27\u00a0\u20b9",
  "3 Bedroom Apartment Outside of City Centre": "40,227.27\u00a0\u20b9",
  "Price per Square Meter to Buy Apartment in City Centre": "240,286.01\u00a0\u20b9",
  "Price per Square Meter to Buy Apartment Outside of Centre": "91,615.42\u00a0\u20b9",
  "Average Monthly Net Salary (After Tax)": "50,274.59\u00a0\u20b9",
  "Annual Mortgage Interest Rate (20-Year Fixed, in %)": "9.57"
}
